{
    "CurrentCate": {
        "CateId": 1,
        "CateName": "教育123123",
        "ImageUrl": "themes/temp/7.jpg",
        "Description": "在这里，可以让孩子找到属于他们的手工创作天地。",
        "RelatedClub": 2
    },

    "CategoryList": [
        {
            "CateId": 11,
            "CateName": "大班"
        },
        {
            "CateId": 21,
            "CateName": "中班"
        },
        {
            "CateId": 32,
            "CateName": "小班"
        },
        {
            "CateId": 43,
            "CateName": "托班"
        }
    ]
}